[{"cohort_month": "2025-01", "new_users": 12874, "cac": 39.29, "payback_month": 1, "ltv_month_6": 67.02}, {"cohort_month": "2025-02", "new_users": 7939, "cac": 47.99, "payback_month": 1, "ltv_month_6": 68.39}, {"cohort_month": "2025-03", "new_users": 4392, "cac": 50.43, "payback_month": 2, "ltv_month_6": 64.61}, {"cohort_month": "2025-04", "new_users": 4134, "cac": 47.92, "payback_month": 2, "ltv_month_6": 59.65}, {"cohort_month": "2025-05", "new_users": 5894, "cac": 51.82, "payback_month": 2, "ltv_month_6": 71.73}, {"cohort_month": "2025-06", "new_users": 4782, "cac": 52.96, "payback_month": 3, "ltv_month_6": 68.15}, {"cohort_month": "2025-07", "new_users": 6883, "cac": 57.47, "payback_month": 3, "ltv_month_6": 71.22}, {"cohort_month": "2025-08", "new_users": 9952, "cac": 58.88, "payback_month": 3, "ltv_month_6": 73.99}, {"cohort_month": "2025-09", "new_users": 7701, "cac": 53.99, "payback_month": 3, "ltv_month_6": 69.86}, {"cohort_month": "2025-10", "new_users": 7549, "cac": 48.61, "payback_month": 1, "ltv_month_6": 71.81}, {"cohort_month": "2025-11", "new_users": 11038, "cac": 48.19, "payback_month": 2, "ltv_month_6": 68.18}, {"cohort_month": "2025-12", "new_users": 12338, "cac": 50.3, "payback_month": 2, "ltv_month_6": 68.05}, {"cohort_month": "2026-01", "new_users": 19894, "cac": 54.59, "payback_month": 2, "ltv_month_6": 69.5}, {"cohort_month": "2026-02", "new_users": 10437, "cac": 83.47, "payback_month": 3, "ltv_month_6": 88.41}, {"cohort_month": "2026-03", "new_users": 10494, "cac": 74.39, "payback_month": null, "ltv_month_6": 60.75}, {"cohort_month": "2026-04", "new_users": 7196, "cac": 74.75, "payback_month": null, "ltv_month_6": 52.76}, {"cohort_month": "2026-05", "new_users": 5124, "cac": 75.67, "payback_month": null, "ltv_month_6": 56.66}]